calc_func.py
syasya_addition.py
syasya_division.py
syasya_multiplication.py
syasya_substraction.py
syasya_calculator-0.0.3.dist-info/LICENSE.txt
syasya_calculator-0.0.3.dist-info/METADATA
syasya_calculator-0.0.3.dist-info/WHEEL
syasya_calculator-0.0.3.dist-info/top_level.txt
syasya_calculator-0.0.3.dist-info/RECORD
