Metadata-Version: 2.1
Name: syasya-calculator
Version: 0.0.3
Summary: calculator
Home-page: UNKNOWN
Author: Syasya Putri
License: UNKNOWN
Platform: UNKNOWN
Requires-Dist: blessings (~=1.7)
